{
	"list-station": [
		{
			"station_id": 1,
			"station_name": "Stasiun Bandung",
			"station_phone": "021-121",
			"street_address": "Jl. Stasiun Barat Kb. Jeruk Kec. Andir Kota Bandung Jawa Barat 40181",
			"city": "Kota Bandung",
			"province": "Jawa Barat",
			"country": "Indonesia"
		},
		{
			"station_id": 2,
			"station_name": "Stasiun Ciranjang",
			"station_phone": "021-121",
			"street_address": "Jl. Stasiun, Ciranjang, Kec. Ciranjang, Kabupaten Cianjur, Jawa Barat 43282",
			"city": "Kabupaten Cianjur",
			"province": "Jawa Barat",
			"country": "Indonesia"
		},
		{
			"station_id": 3,
			"station_name": "Stasiun Angbar",
			"station_phone": "021-121",
			"street_address": "Jl. Stasiun, Angbar, Kec. Angbar, Kabupaten Cianjur, Jawa Barat 43282",
			"city": "Kabupaten Cianjur",
			"province": "Jawa Barat",
			"country": "Indonesia"
		},
		{
			"station_id": 4,
			"station_name": "Stasiun Cimekar",
			"station_phone": "021-121",
			"street_address": "Cibiru Hilir, Cileunyi, Bandung, Jawa Barat, Indonesia, Jawa Barat 40626",
			"city": "Kota Bandung",
			"province": "Jawa Barat",
			"country": "Indonesia"
		}
	],
	"list-camera": [
		{
			"station_id": 1,
			"station_name": "Stasiun Bandung",
			"station_phone": "021-121",
			"street_address": "Jl. Stasiun Barat Kb. Jeruk Kec. Andir Kota Bandung Jawa Barat 40181",
			"city": "Kota Bandung",
			"province": "Jawa Barat",
			"country": "Indonesia",
			"cameras": [
				{
					"id": "1",
					"name": "TRAV PERON 1 BAWAH",
					"url": "http://cctv3.sigma.my.id:5080/stBD/streams/970166039821732819439469.m3u8"
				},
				{
					"id": "2",
					"name": "TRAV PERON 3 BAWAH",
					"url": "http://cctv3.sigma.my.id:5080/stBD/streams/288650179155545077333726.m3u8"
				},
				{
					"id": "3",
					"name": "TRAV PERON 5 BAWAH",
					"url": "http://cctv3.sigma.my.id:5080/stBD/streams/868247723886849361997412.m3u8"
				},
				{
					"id": "4",
					"name": "TRAV PERON 7 BAWAH",
					"url": "http://cctv3.sigma.my.id:5080/stBD/streams/969874479643632693841434.m3u8"
				},
				{
					"id": "5",
					"name": "HALL",
					"url": "http://cctv3.sigma.my.id:5080/stBD/streams/824815660258769737103119.m3u8"
				},
				{
					"id": "6",
					"name": "TRAV PERON HALL ATAS",
					"url": "http://cctv3.sigma.my.id:5080/stBD/streams/270725978814837058273546.m3u8"
				},
				{
					"id": "7",
					"name": "TRAV PERON 1 ATAS",
					"url": "http://cctv3.sigma.my.id:5080/stBD/streams/270725978814837058273546.m3u8"
				},
				{
					"id": "8",
					"name": "TRAV PERON 3 ATAS",
					"url": "http://cctv3.sigma.my.id:5080/stBD/streams/483067876133532544626378.m3u8"
				},
				{
					"id": "9",
					"name": "TRAV PERON 5 ATAS",
					"url": "http://cctv3.sigma.my.id:5080/stBD/streams/088723240826193747864159.m3u8"
				},
				{
					"id": "10",
					"name": "TRAV PERON 7 ATAS",
					"url": "http://cctv3.sigma.my.id:5080/stBD/streams/124714111743599217072137.m3u8"
				},
				{
					"id": "11",
					"name": "SKYBRIDGE POJOK UTARA",
					"url": "http://cctv3.sigma.my.id:5080/stBD/streams/630028030554191865669077.m3u8"
				},
				{
					"id": "12",
					"name": "SKYBRIDGE POJOK SELATAN",
					"url": "http://cctv3.sigma.my.id:5080/stBD/streams/701054868863149728181309.m3u8"
				},
				{
					"id": "13",
					"name": "SINYAL MASUK TIMUR",
					"url": "http://cctv3.sigma.my.id:5080/stBD/streams/778207896459696660959517.m3u8"
				},
				{
					"id": "14",
					"name": "SINYAL KELUAR TIMUR",
					"url": "http://cctv3.sigma.my.id:5080/stBD/streams/812448650260481456309412.m3u8"
				},
				{
					"id": "15",
					"name": "RUANG TUNGGU PENUMPANG PERON",
					"url": "http://cctv3.sigma.my.id:5080/stBD/streams/dahua01-cam01.m3u8"
				},
				{
					"id": "16",
					"name": "HALL RUANG TUNGGU PENUMPANG",
					"url": "http://cctv3.sigma.my.id:5080/stBD/streams/dahua01-cam02.m3u8"
				},
				{
					"id": "17",
					"name": "PERON DI SAMPING ROTI O",
					"url": "http://cctv3.sigma.my.id:5080/stBD/streams/dahua01-cam03.m3u8"
				},
				{
					"id": "18",
					"name": "RUANG TUNGGU DEPAN PINTU MASUK",
					"url": "http://cctv3.sigma.my.id:5080/stBD/streams/dahua01-cam04.m3u8"
				},
				{
					"id": "19",
					"name": "HALL DEPAN RUANG KEPALA STASIUN",
					"url": "http://cctv3.sigma.my.id:5080/stBD/streams/dahua01-cam05.m3u8"
				},
				{
					"id": "20",
					"name": "PINTU MASUK",
					"url": "http://cctv3.sigma.my.id:5080/stBD/streams/dahua01-cam06.m3u8"
				}
			]
		},
		{
			"station_id": 2,
			"station_name": "Stasiun Ciranjang",
			"station_phone": "021-121",
			"street_address": "Jl. Stasiun, Ciranjang, Kec. Ciranjang, Kabupaten Cianjur, Jawa Barat 43282",
			"city": "Kabupaten Cianjur",
			"province": "Jawa Barat",
			"country": "Indonesia",
			"cameras": [
				{
					"id": "1",
					"name": "JALUR ARAH KE BARAT",
					"url": "http://cctv3.sigma.my.id:5080/stCRJ/streams/359312103044122463061638.m3u8"
				},
				{
					"id": "2",
					"name": "JALUR ARAH KE TIMUR",
					"url": "http://cctv3.sigma.my.id:5080/stCRJ/streams/344505261289578566279432.m3u8"
				},
				{
					"id": "3",
					"name": "RUANG TUNGGU",
					"url": "http://cctv3.sigma.my.id:5080/stCRJ/streams/700715351750204185439525.m3u8"
				},
				{
					"id": "4",
					"name": "PINTU KELUAR",
					"url": "http://cctv3.sigma.my.id:5080/stCRJ/streams/279239846553266693016275.m3u8"
				}
			]
		},
		{
			"station_id": 3,
			"station_name": "Stasiun Angbar",
			"station_phone": "021-121",
			"street_address": "Jl. Stasiun, Angbar, Kec. Angbar, Kabupaten Cianjur, Jawa Barat 43282",
			"city": "Kabupaten Cianjur",
			"province": "Jawa Barat",
			"country": "Indonesia",
			"cameras": [
				{
					"id": "1",
					"name": "KANTOR",
					"url": "http://cctv3.sigma.my.id:5080/stANG/streams/172482818827854110708880.m3u8"
				},
				{
					"id": "2",
					"name": "PARKIR",
					"url": "http://cctv3.sigma.my.id:5080/stANG/streams/530760717639066733405191.m3u8"
				},
				{
					"id": "3",
					"name": "REL",
					"url": "http://cctv3.sigma.my.id:5080/stANG/streams/945230695120686804840706.m3u8"
				},
				{
					"id": "4",
					"name": "PINTU MASUK",
					"url": "http://cctv3.sigma.my.id:5080/stANG/streams/670301260687069998559914.m3u8"
				},
				{
					"id": "5",
					"name": "ADMINISTRASI",
					"url": "http://cctv3.sigma.my.id:5080/stANG/streams/462562065663214689932154.m3u8"
				},
				{
					"id": "6",
					"name": "PINTU KELUAR",
					"url": "http://cctv3.sigma.my.id:5080/stANG/streams/724851936763847872897117.m3u8"
				}
			]
		},
		{
			"station_id": 4,
			"station_name": "Stasiun Cimekar",
			"station_phone": "021-121",
			"street_address": "Cibiru Hilir, Cileunyi, Bandung, Jawa Barat, Indonesia, Jawa Barat 40626",
			"city": "Kota Bandung",
			"province": "Jawa Barat",
			"country": "Indonesia",
			"cameras": [
				{
					"id": "1",
					"name": "PERON TIMUR CMK",
					"url": "http://cctv3.sigma.my.id:5080/stCMK/streams/dahua01-cam01.m3u8"
				},
				{
					"id": "2",
					"name": "MUSHOLA CMK",
					"url": "http://cctv3.sigma.my.id:5080/stCMK/streams/dahua01-cam02.m3u8"
				},
				{
					"id": "3",
					"name": "LOKET CMK",
					"url": "http://cctv3.sigma.my.id:5080/stCMK/streams/dahua01-cam03.m3u8"
				},
				{
					"id": "4",
					"name": "ANTRIAN LOKET CMK",
					"url": "http://cctv3.sigma.my.id:5080/stCMK/streams/dahua01-cam04.m3u8"
				}
			]
		}
	]
}